{"nodes": [{"name": "streetwear", "value": 494}, {"name": "skincareaddiction", "value": 408}, {"name": "frugalmalefashion", "value": 263}, {"name": "thriftstorehauls", "value": 113}, {"name": "sneakers", "value": 232}, {"name": "femalefashionadvice", "value": 325}, {"name": "asianbeauty", "value": 234}, {"name": "makeupaddiction", "value": 538}, {"name": "watches", "value": 307}, {"name": "malefashionadvice", "value": 1279}, {"name": "bitcoin", "value": 5983}, {"name": "gadgets", "value": 445}, {"name": "pcmasterrace", "value": 4795}, {"name": "programming", "value": 1704}, {"name": "google", "value": 265}, {"name": "internetisbeautiful", "value": 576}, {"name": "javascript", "value": 322}, {"name": "hacking", "value": 222}, {"name": "technology", "value": 4016}, {"name": "learnprogramming", "value": 953}, {"name": "techsupport", "value": 2185}, {"name": "apple", "value": 1177}], "links": [{"source": "watches", "target": "malefashionadvice", "value": 16, "sentiment": 10}, {"source": "malefashionadvice", "target": "frugalmalefashion", "value": 73, "sentiment": 10}, {"source": "makeupaddiction", "target": "skincareaddiction", "value": 22, "sentiment": 10}, {"source": "malefashionadvice", "target": "femalefashionadvice", "value": 182, "sentiment": 10}, {"source": "malefashionadvice", "target": "streetwear", "value": 41, "sentiment": 9}, {"source": "bitcoin", "target": "technology", "value": 60, "sentiment": 9}, {"source": "skincareaddiction", "target": "asianbeauty", "value": 80, "sentiment": 10}, {"source": "frugalmalefashion", "target": "watches", "value": 3, "sentiment": 10}, {"source": "bitcoin", "target": "malefashionadvice", "value": 2, "sentiment": 10}, {"source": "asianbeauty", "target": "makeupaddiction", "value": 14, "sentiment": 9}, {"source": "techsupport", "target": "pcmasterrace", "value": 106, "sentiment": 10}, {"source": "malefashionadvice", "target": "skincareaddiction", "value": 2, "sentiment": 10}, {"source": "learnprogramming", "target": "programming", "value": 63, "sentiment": 10}, {"source": "makeupaddiction", "target": "femalefashionadvice", "value": 4, "sentiment": 10}, {"source": "hacking", "target": "techsupport", "value": 6, "sentiment": 10}, {"source": "apple", "target": "technology", "value": 27, "sentiment": 10}, {"source": "techsupport", "target": "technology", "value": 12, "sentiment": 10}, {"source": "learnprogramming", "target": "javascript", "value": 16, "sentiment": 10}, {"source": "bitcoin", "target": "hacking", "value": 4, "sentiment": 8}, {"source": "watches", "target": "gadgets", "value": 1, "sentiment": 10}, {"source": "malefashionadvice", "target": "sneakers", "value": 13, "sentiment": 10}, {"source": "techsupport", "target": "watches", "value": 1, "sentiment": 0}, {"source": "apple", "target": "gadgets", "value": 2, "sentiment": 10}, {"source": "bitcoin", "target": "programming", "value": 11, "sentiment": 10}, {"source": "bitcoin", "target": "apple", "value": 8, "sentiment": 9}, {"source": "learnprogramming", "target": "bitcoin", "value": 1, "sentiment": 10}, {"source": "skincareaddiction", "target": "femalefashionadvice", "value": 1, "sentiment": 10}, {"source": "learnprogramming", "target": "google", "value": 1, "sentiment": 10}, {"source": "javascript", "target": "bitcoin", "value": 2, "sentiment": 10}, {"source": "technology", "target": "programming", "value": 12, "sentiment": 9}, {"source": "technology", "target": "gadgets", "value": 7, "sentiment": 10}, {"source": "learnprogramming", "target": "internetisbeautiful", "value": 4, "sentiment": 10}, {"source": "techsupport", "target": "apple", "value": 1, "sentiment": 10}, {"source": "hacking", "target": "technology", "value": 6, "sentiment": 10}, {"source": "sneakers", "target": "streetwear", "value": 20, "sentiment": 10}, {"source": "apple", "target": "internetisbeautiful", "value": 2, "sentiment": 10}, {"source": "bitcoin", "target": "internetisbeautiful", "value": 2, "sentiment": 10}, {"source": "techsupport", "target": "google", "value": 3, "sentiment": 10}, {"source": "javascript", "target": "programming", "value": 21, "sentiment": 10}, {"source": "learnprogramming", "target": "techsupport", "value": 2, "sentiment": 10}, {"source": "femalefashionadvice", "target": "streetwear", "value": 3, "sentiment": 10}, {"source": "google", "target": "technology", "value": 6, "sentiment": 8}, {"source": "streetwear", "target": "frugalmalefashion", "value": 6, "sentiment": 10}, {"source": "asianbeauty", "target": "femalefashionadvice", "value": 1, "sentiment": 10}, {"source": "pcmasterrace", "target": "technology", "value": 9, "sentiment": 9}, {"source": "bitcoin", "target": "pcmasterrace", "value": 5, "sentiment": 8}, {"source": "programming", "target": "sneakers", "value": 1, "sentiment": 10}, {"source": "hacking", "target": "google", "value": 1, "sentiment": 0}, {"source": "sneakers", "target": "thriftstorehauls", "value": 3, "sentiment": 10}, {"source": "bitcoin", "target": "techsupport", "value": 1, "sentiment": 0}, {"source": "google", "target": "apple", "value": 1, "sentiment": 10}, {"source": "hacking", "target": "learnprogramming", "value": 1, "sentiment": 10}, {"source": "pcmasterrace", "target": "apple", "value": 7, "sentiment": 9}, {"source": "google", "target": "bitcoin", "value": 4, "sentiment": 10}, {"source": "programming", "target": "techsupport", "value": 1, "sentiment": 10}, {"source": "programming", "target": "apple", "value": 2, "sentiment": 10}, {"source": "pcmasterrace", "target": "internetisbeautiful", "value": 2, "sentiment": 10}, {"source": "programming", "target": "hacking", "value": 3, "sentiment": 10}, {"source": "programming", "target": "pcmasterrace", "value": 1, "sentiment": 10}, {"source": "streetwear", "target": "pcmasterrace", "value": 1, "sentiment": 10}, {"source": "hacking", "target": "gadgets", "value": 1, "sentiment": 10}, {"source": "programming", "target": "internetisbeautiful", "value": 2, "sentiment": 10}, {"source": "sneakers", "target": "frugalmalefashion", "value": 1, "sentiment": 10}, {"source": "malefashionadvice", "target": "thriftstorehauls", "value": 1, "sentiment": 10}, {"source": "streetwear", "target": "thriftstorehauls", "value": 1, "sentiment": 10}, {"source": "gadgets", "target": "pcmasterrace", "value": 1, "sentiment": 10}, {"source": "makeupaddiction", "target": "pcmasterrace", "value": 1, "sentiment": 10}]}